RISC-V Processor/src/data_memory.v
module data_memory (
    input wire clk,
    input wire [31:0] address,
    input wire [31:0] write_data,
    input wire mem_write,
    output wire [31:0] read_data
);

reg [31:0] memory [0:1023]; // 1024 words of 32-bit memory

always @(posedge clk) begin
    if (mem_write)
        memory[address[11:2]] <= write_data;
end

assign read_data = memory[address[11:2]];

endmodule

RISC-V Processor/src/immediate_gen.v
module immediate_gen (
    input wire [31:0] instruction,
    output reg [31:0] immediate
);

wire [6:0] opcode = instruction[6:0];

always @(*) begin
    case (opcode)
        7'b0010011: immediate = {{20{instruction[31]}}, instruction[31:20]}; // I-type
        7'b0000011: immediate = {{20{instruction[31]}}, instruction[31:20]}; // Load
        7'b0100011: immediate = {{20{instruction[31]}}, instruction[31:25], instruction[11:7]}; // Store
        7'b1100011: immediate = {{20{instruction[31]}}, instruction[7], instruction[30:25], instruction[11:8], 1'b0}; // Branch
        default: immediate = 32'h0;
    endcase
end

endmodule

src/control_unit.v
module control_unit (
    input wire [6:0] opcode,
    input wire [2:0] funct3,
    input wire [6:0] funct7,
    output reg [1:0] alu_op,
    output reg mem_write,
    output reg mem_to_reg,
    output reg alu_src,
    output reg reg_write,
    output reg branch
);

// Opcodes
parameter R_TYPE = 7'b0110011;
parameter I_TYPE = 7'b0010011;
parameter LW     = 7'b0000011;
parameter SW     = 7'b0100011;
parameter BRANCH = 7'b1100011;

always @(*) begin
    case (opcode)
        R_TYPE: begin
            alu_op = 2'b10;     // R-type ALU operation
            mem_write = 1'b0;   // No memory write
            mem_to_reg = 1'b0;  // ALU result to register
            alu_src = 1'b0;     // Use register as second operand
            reg_write = 1'b1;   // Write result to register
            branch = 1'b0;      // Not a branch instruction
        end
        I_TYPE: begin
            alu_op = 2'b10;     // I-type ALU operation
            mem_write = 1'b0;
            mem_to_reg = 1'b0;
            alu_src = 1'b1;     // Use immediate as second operand
            reg_write = 1'b1;
            branch = 1'b0;
        end
        LW: begin
            alu_op = 2'b00;     // Add for address calculation
            mem_write = 1'b0;
            mem_to_reg = 1'b1;  // Memory to register
            alu_src = 1'b1;
            reg_write = 1'b1;
            branch = 1'b0;
        end
        SW: begin
            alu_op = 2'b00;
            mem_write = 1'b1;   // Write to memory
            mem_to_reg = 1'bx;  // Don't care
            alu_src = 1'b1;
            reg_write = 1'b0;   // No register write
            branch = 1'b0;
        end
        BRANCH: begin
            alu_op = 2'b01;     // Branch comparison
            mem_write = 1'b0;
            mem_to_reg = 1'bx;
            alu_src = 1'b0;
            reg_write = 1'b0;
            branch = 1'b1;      // Branch instruction
        end
        default: begin
            alu_op = 2'b00;
            mem_write = 1'b0;
            mem_to_reg = 1'b0;
            alu_src = 1'b0;
            reg_write = 1'b0;
            branch = 1'b0;
        end
    endcase
end

endmodule

src/alu.v
module alu (
    input wire [31:0] operand_a,
    input wire [31:0] operand_b,
    input wire [3:0] alu_control,
    output reg [31:0] result,
    output wire zero_flag
);

// ALU Operation Codes
parameter ALU_ADD = 4'b0000;
parameter ALU_SUB = 4'b0001;
parameter ALU_AND = 4'b0010;
parameter ALU_OR  = 4'b0011;
parameter ALU_SLT = 4'b0100;  // Set Less Than

always @(*) begin
    case (alu_control)
        ALU_ADD: result = operand_a + operand_b;
        ALU_SUB: result = operand_a - operand_b;
        ALU_AND: result = operand_a & operand_b;
        ALU_OR:  result = operand_a | operand_b;
        ALU_SLT: result = ($signed(operand_a) < $signed(operand_b)) ? 32'd1 : 32'd0;
        default: result = 32'h0;
    endcase
end

assign zero_flag = (result == 32'h0);

endmodule

src/register_file.v
module register_file (
    input wire clk,
    input wire [4:0] read_reg1,
    input wire [4:0] read_reg2,
    input wire [4:0] write_reg,
    input wire [31:0] write_data,
    input wire reg_write,
    output wire [31:0] read_data1,
    output wire [31:0] read_data2
);

reg [31:0] registers [0:31];

// Initialize registers
integer i;
initial begin
    for (i = 0; i < 32; i = i + 1)
        registers[i] = 32'h0;
end

// Write operation
always @(posedge clk) begin
    if (reg_write && write_reg != 5'b0)
        registers[write_reg] <= write_data;
end

// Read operations
assign read_data1 = (read_reg1 == 5'b0) ? 32'h0 : registers[read_reg1];
assign read_data2 = (read_reg2 == 5'b0) ? 32'h0 : registers[read_reg2];

endmodule

RISC-V Processor/src/instruction_memory.v
module instruction_memory (
    input wire [31:0] pc,
    output wire [31:0] instruction
);

reg [31:0] memory [0:1023]; // 1024 words of 32-bit instructions

initial begin
    // Load program into memory
    $readmemh("program.hex", memory);
end

assign instruction = memory[pc[11:2]]; // Word-aligned access

endmodule

RISC-V Processor/src/program_counter.v
module program_counter (
    input wire clk,
    input wire rst,
    input wire [31:0] pc_next,
    output reg [31:0] pc_current
);

always @(posedge clk or posedge rst) begin
    if (rst)
        pc_current <= 32'h0;
    else
        pc_current <= pc_next;
end

endmodule

src/riscv_top.v
module riscv_top (
    input wire clk,
    input wire rst
);

// Internal signals
wire [31:0] pc_current, pc_next, instruction;
wire [31:0] reg_write_data, read_data1, read_data2;
wire [31:0] alu_result, immediate, data_memory_out;
wire [3:0] alu_control;
wire zero_flag, branch, mem_write, mem_to_reg, alu_src, reg_write;
wire [1:0] alu_op;

// Program Counter
program_counter pc_module (
    .clk(clk),
    .rst(rst),
    .pc_next(pc_next),
    .pc_current(pc_current)
);

// Instruction Memory
instruction_memory instr_mem (
    .pc(pc_current),
    .instruction(instruction)
);

// Register File
register_file reg_file (
    .clk(clk),
    .read_reg1(instruction[19:15]),
    .read_reg2(instruction[24:20]),
    .write_reg(instruction[11:7]),
    .write_data(reg_write_data),
    .reg_write(reg_write),
    .read_data1(read_data1),
    .read_data2(read_data2)
);

// ALU
alu alu_module (
    .operand_a(read_data1),
    .operand_b(alu_src ? immediate : read_data2),
    .alu_control(alu_control),
    .result(alu_result),
    .zero_flag(zero_flag)
);

// Control Unit
control_unit ctrl_unit (
    .opcode(instruction[6:0]),
    .funct3(instruction[14:12]),
    .funct7(instruction[31:25]),
    .alu_op(alu_op),
    .mem_write(mem_write),
    .mem_to_reg(mem_to_reg),
    .alu_src(alu_src),
    .reg_write(reg_write),
    .branch(branch)
);

// Immediate Generator
immediate_gen imm_gen (
    .instruction(instruction),
    .immediate(immediate)
);

// Data Memory
data_memory data_mem (
    .clk(clk),
    .address(alu_result),
    .write_data(read_data2),
    .mem_write(mem_write),
    .read_data(data_memory_out)
);

// Next PC calculation
assign pc_next = pc_current + ((branch & zero_flag) ? immediate : 32'd4);

// Write back
assign reg_write_data = mem_to_reg ? data_memory_out : alu_result;

endmodule

RISC-V Processor/testbench/riscv_tb.v
module riscv_tb;
    reg clk;
    reg rst;
    
    // Instantiate the top module
    riscv_top dut (
        .clk(clk),
        .rst(rst)
    );
    
    // Clock generation
    initial begin
        clk = 0;
        forever #5 clk = ~clk;
    end
    
    // Test stimulus
    initial begin
        // Reset
        rst = 1;
        #10 rst = 0;
        
        // Run for some cycles
        #1000;
        
        // End simulation
        $finish;
    end
    
    // Waveform generation
    initial begin
        $dumpfile("riscv_test.vcd");
        $dumpvars(0, riscv_tb);
    end
    
    // Monitor important signals
    always @(posedge clk) begin
    $display("Time=%0t PC=%h Instruction=%h", 
             $time, dut.pc_current, dut.instruction);
    $display("Registers: x1=%h x2=%h x3=%h x4=%h",
             dut.reg_file.registers[1],
             dut.reg_file.registers[2],
             dut.reg_file.registers[3],
             dut.reg_file.registers[4]);
    end
endmodule

simulation/riscv_test.vcd
$date
	Fri Oct 11 21:52:05 2024
$end
$version
	Icarus Verilog
$end
$timescale
	1s
$end
$scope module riscv_tb $end
$var reg 1 ! clk $end
$var reg 1 " rst $end
$scope module dut $end
$var wire 4 # alu_control [3:0] $end
$var wire 1 ! clk $end
$var wire 1 " rst $end
$var wire 1 $ zero_flag $end
$var wire 32 % reg_write_data [31:0] $end
$var wire 1 & reg_write $end
$var wire 32 ' read_data2 [31:0] $end
$var wire 32 ( read_data1 [31:0] $end
$var wire 32 ) pc_next [31:0] $end
$var wire 32 * pc_current [31:0] $end
$var wire 1 + mem_write $end
$var wire 1 , mem_to_reg $end
$var wire 32 - instruction [31:0] $end
$var wire 32 . immediate [31:0] $end
$var wire 32 / data_memory_out [31:0] $end
$var wire 1 0 branch $end
$var wire 1 1 alu_src $end
$var wire 32 2 alu_result [31:0] $end
$var wire 2 3 alu_op [1:0] $end
$scope module alu_module $end
$var wire 4 4 alu_control [3:0] $end
$var wire 32 5 operand_b [31:0] $end
$var wire 1 $ zero_flag $end
$var wire 32 6 operand_a [31:0] $end
$var parameter 4 7 ALU_ADD $end
$var parameter 4 8 ALU_AND $end
$var parameter 4 9 ALU_OR $end
$var parameter 4 : ALU_SLT $end
$var parameter 4 ; ALU_SUB $end
$var reg 32 < result [31:0] $end
$upscope $end
$scope module ctrl_unit $end
$var wire 3 = funct3 [2:0] $end
$var wire 7 > funct7 [6:0] $end
$var wire 7 ? opcode [6:0] $end
$var parameter 7 @ BRANCH $end
$var parameter 7 A I_TYPE $end
$var parameter 7 B LW $end
$var parameter 7 C R_TYPE $end
$var parameter 7 D SW $end
$var reg 2 E alu_op [1:0] $end
$var reg 1 1 alu_src $end
$var reg 1 0 branch $end
$var reg 1 , mem_to_reg $end
$var reg 1 + mem_write $end
$var reg 1 & reg_write $end
$upscope $end
$scope module data_mem $end
$var wire 32 F address [31:0] $end
$var wire 1 ! clk $end
$var wire 1 + mem_write $end
$var wire 32 G read_data [31:0] $end
$var wire 32 H write_data [31:0] $end
$upscope $end
$scope module imm_gen $end
$var wire 7 I opcode [6:0] $end
$var wire 32 J instruction [31:0] $end
$var reg 32 K immediate [31:0] $end
$upscope $end
$scope module instr_mem $end
$var wire 32 L instruction [31:0] $end
$var wire 32 M pc [31:0] $end
$upscope $end
$scope module pc_module $end
$var wire 1 ! clk $end
$var wire 32 N pc_next [31:0] $end
$var wire 1 " rst $end
$var reg 32 O pc_current [31:0] $end
$upscope $end
$scope module reg_file $end
$var wire 1 ! clk $end
$var wire 5 P read_reg1 [4:0] $end
$var wire 5 Q read_reg2 [4:0] $end
$var wire 1 & reg_write $end
$var wire 32 R write_data [31:0] $end
$var wire 5 S write_reg [4:0] $end
$var wire 32 T read_data2 [31:0] $end
$var wire 32 U read_data1 [31:0] $end
$var integer 32 V i [31:0] $end
$upscope $end
$upscope $end
$upscope $end
$enddefinitions $end
$comment Show the parameter values. $end
$dumpall
b100011 D
b110011 C
b11 B
b10011 A
b1100011 @
b1 ;
b100 :
b11 9
b10 8
b0 7
$end
#0
$dumpvars
b100000 V
b0 U
b0 T
b1 S
b0 R
b101 Q
b0 P
b0 O
b100 N
b0 M
b10100000000000010010011 L
b101 K
b10100000000000010010011 J
b10011 I
b0 H
bx G
b0 F
b10 E
b10011 ?
b0 >
b0 =
b0 <
b0 6
b101 5
bz 4
b10 3
b0 2
11
00
bx /
b101 .
b10100000000000010010011 -
0,
0+
b0 *
b100 )
b0 (
b0 '
1&
b0 %
1$
bz #
1"
0!
$end
#5
1!
#10
0!
0"
#15
0&
01
b0 3
b0 E
bx '
bx H
bx T
bx (
bx 6
bx U
bx 5
bx I
bx >
bx =
bx ?
bx S
bx Q
bx P
b0 .
b0 K
bx -
bx J
bx L
b1000 )
b1000 N
b100 *
b100 M
b100 O
1!
#20
0!
#25
b1100 )
b1100 N
b1000 *
b1000 M
b1000 O
1!
#30
0!
#35
b10000 )
b10000 N
b1100 *
b1100 M
b1100 O
1!
#40
0!
#45
b10100 )
b10100 N
b10000 *
b10000 M
b10000 O
1!
#50
0!
#55
b11000 )
b11000 N
b10100 *
b10100 M
b10100 O
1!
#60
0!
#65
b11100 )
b11100 N
b11000 *
b11000 M
b11000 O
1!
#70
0!
#75
b100000 )
b100000 N
b11100 *
b11100 M
b11100 O
1!
#80
0!
#85
b100100 )
b100100 N
b100000 *
b100000 M
b100000 O
1!
#90
0!
#95
b101000 )
b101000 N
b100100 *
b100100 M
b100100 O
1!
#100
0!
#105
b101100 )
b101100 N
b101000 *
b101000 M
b101000 O
1!
#110
0!
#115
b110000 )
b110000 N
b101100 *
b101100 M
b101100 O
1!
#120
0!
#125
b110100 )
b110100 N
b110000 *
b110000 M
b110000 O
1!
#130
0!
#135
b111000 )
b111000 N
b110100 *
b110100 M
b110100 O
1!
#140
0!
#145
b111100 )
b111100 N
b111000 *
b111000 M
b111000 O
1!
#150
0!
#155
b1000000 )
b1000000 N
b111100 *
b111100 M
b111100 O
1!
#160
0!
#165
b1000100 )
b1000100 N
b1000000 *
b1000000 M
b1000000 O
1!
#170
0!
#175
b1001000 )
b1001000 N
b1000100 *
b1000100 M
b1000100 O
1!
#180
0!
#185
b1001100 )
b1001100 N
b1001000 *
b1001000 M
b1001000 O
1!
#190
0!
#195
b1010000 )
b1010000 N
b1001100 *
b1001100 M
b1001100 O
1!
#200
0!
#205
b1010100 )
b1010100 N
b1010000 *
b1010000 M
b1010000 O
1!
#210
0!
#215
b1011000 )
b1011000 N
b1010100 *
b1010100 M
b1010100 O
1!
#220
0!
#225
b1011100 )
b1011100 N
b1011000 *
b1011000 M
b1011000 O
1!
#230
0!
#235
b1100000 )
b1100000 N
b1011100 *
b1011100 M
b1011100 O
1!
#240
0!
#245
b1100100 )
b1100100 N
b1100000 *
b1100000 M
b1100000 O
1!
#250
0!
#255
b1101000 )
b1101000 N
b1100100 *
b1100100 M
b1100100 O
1!
#260
0!
#265
b1101100 )
b1101100 N
b1101000 *
b1101000 M
b1101000 O
1!
#270
0!
#275
b1110000 )
b1110000 N
b1101100 *
b1101100 M
b1101100 O
1!
#280
0!
#285
b1110100 )
b1110100 N
b1110000 *
b1110000 M
b1110000 O
1!
#290
0!
#295
b1111000 )
b1111000 N
b1110100 *
b1110100 M
b1110100 O
1!
#300
0!
#305
b1111100 )
b1111100 N
b1111000 *
b1111000 M
b1111000 O
1!
#310
0!
#315
b10000000 )
b10000000 N
b1111100 *
b1111100 M
b1111100 O
1!
#320
0!
#325
b10000100 )
b10000100 N
b10000000 *
b10000000 M
b10000000 O
1!
#330
0!
#335
b10001000 )
b10001000 N
b10000100 *
b10000100 M
b10000100 O
1!
#340
0!
#345
b10001100 )
b10001100 N
b10001000 *
b10001000 M
b10001000 O
1!
#350
0!
#355
b10010000 )
b10010000 N
b10001100 *
b10001100 M
b10001100 O
1!
#360
0!
#365
b10010100 )
b10010100 N
b10010000 *
b10010000 M
b10010000 O
1!
#370
0!
#375
b10011000 )
b10011000 N
b10010100 *
b10010100 M
b10010100 O
1!
#380
0!
#385
b10011100 )
b10011100 N
b10011000 *
b10011000 M
b10011000 O
1!
#390
0!
#395
b10100000 )
b10100000 N
b10011100 *
b10011100 M
b10011100 O
1!
#400
0!
#405
b10100100 )
b10100100 N
b10100000 *
b10100000 M
b10100000 O
1!
#410
0!
#415
b10101000 )
b10101000 N
b10100100 *
b10100100 M
b10100100 O
1!
#420
0!
#425
b10101100 )
b10101100 N
b10101000 *
b10101000 M
b10101000 O
1!
#430
0!
#435
b10110000 )
b10110000 N
b10101100 *
b10101100 M
b10101100 O
1!
#440
0!
#445
b10110100 )
b10110100 N
b10110000 *
b10110000 M
b10110000 O
1!
#450
0!
#455
b10111000 )
b10111000 N
b10110100 *
b10110100 M
b10110100 O
1!
#460
0!
#465
b10111100 )
b10111100 N
b10111000 *
b10111000 M
b10111000 O
1!
#470
0!
#475
b11000000 )
b11000000 N
b10111100 *
b10111100 M
b10111100 O
1!
#480
0!
#485
b11000100 )
b11000100 N
b11000000 *
b11000000 M
b11000000 O
1!
#490
0!
#495
b11001000 )
b11001000 N
b11000100 *
b11000100 M
b11000100 O
1!
#500
0!
#505
b11001100 )
b11001100 N
b11001000 *
b11001000 M
b11001000 O
1!
#510
0!
#515
b11010000 )
b11010000 N
b11001100 *
b11001100 M
b11001100 O
1!
#520
0!
#525
b11010100 )
b11010100 N
b11010000 *
b11010000 M
b11010000 O
1!
#530
0!
#535
b11011000 )
b11011000 N
b11010100 *
b11010100 M
b11010100 O
1!
#540
0!
#545
b11011100 )
b11011100 N
b11011000 *
b11011000 M
b11011000 O
1!
#550
0!
#555
b11100000 )
b11100000 N
b11011100 *
b11011100 M
b11011100 O
1!
#560
0!
#565
b11100100 )
b11100100 N
b11100000 *
b11100000 M
b11100000 O
1!
#570
0!
#575
b11101000 )
b11101000 N
b11100100 *
b11100100 M
b11100100 O
1!
#580
0!
#585
b11101100 )
b11101100 N
b11101000 *
b11101000 M
b11101000 O
1!
#590
0!
#595
b11110000 )
b11110000 N
b11101100 *
b11101100 M
b11101100 O
1!
#600
0!
#605
b11110100 )
b11110100 N
b11110000 *
b11110000 M
b11110000 O
1!
#610
0!
#615
b11111000 )
b11111000 N
b11110100 *
b11110100 M
b11110100 O
1!
#620
0!
#625
b11111100 )
b11111100 N
b11111000 *
b11111000 M
b11111000 O
1!
#630
0!
#635
b100000000 )
b100000000 N
b11111100 *
b11111100 M
b11111100 O
1!
#640
0!
#645
b100000100 )
b100000100 N
b100000000 *
b100000000 M
b100000000 O
1!
#650
0!
#655
b100001000 )
b100001000 N
b100000100 *
b100000100 M
b100000100 O
1!
#660
0!
#665
b100001100 )
b100001100 N
b100001000 *
b100001000 M
b100001000 O
1!
#670
0!
#675
b100010000 )
b100010000 N
b100001100 *
b100001100 M
b100001100 O
1!
#680
0!
#685
b100010100 )
b100010100 N
b100010000 *
b100010000 M
b100010000 O
1!
#690
0!
#695
b100011000 )
b100011000 N
b100010100 *
b100010100 M
b100010100 O
1!
#700
0!
#705
b100011100 )
b100011100 N
b100011000 *
b100011000 M
b100011000 O
1!
#710
0!
#715
b100100000 )
b100100000 N
b100011100 *
b100011100 M
b100011100 O
1!
#720
0!
#725
b100100100 )
b100100100 N
b100100000 *
b100100000 M
b100100000 O
1!
#730
0!
#735
b100101000 )
b100101000 N
b100100100 *
b100100100 M
b100100100 O
1!
#740
0!
#745
b100101100 )
b100101100 N
b100101000 *
b100101000 M
b100101000 O
1!
#750
0!
#755
b100110000 )
b100110000 N
b100101100 *
b100101100 M
b100101100 O
1!
#760
0!
#765
b100110100 )
b100110100 N
b100110000 *
b100110000 M
b100110000 O
1!
#770
0!
#775
b100111000 )
b100111000 N
b100110100 *
b100110100 M
b100110100 O
1!
#780
0!
#785
b100111100 )
b100111100 N
b100111000 *
b100111000 M
b100111000 O
1!
#790
0!
#795
b101000000 )
b101000000 N
b100111100 *
b100111100 M
b100111100 O
1!
#800
0!
#805
b101000100 )
b101000100 N
b101000000 *
b101000000 M
b101000000 O
1!
#810
0!
#815
b101001000 )
b101001000 N
b101000100 *
b101000100 M
b101000100 O
1!
#820
0!
#825
b101001100 )
b101001100 N
b101001000 *
b101001000 M
b101001000 O
1!
#830
0!
#835
b101010000 )
b101010000 N
b101001100 *
b101001100 M
b101001100 O
1!
#840
0!
#845
b101010100 )
b101010100 N
b101010000 *
b101010000 M
b101010000 O
1!
#850
0!
#855
b101011000 )
b101011000 N
b101010100 *
b101010100 M
b101010100 O
1!
#860
0!
#865
b101011100 )
b101011100 N
b101011000 *
b101011000 M
b101011000 O
1!
#870
0!
#875
b101100000 )
b101100000 N
b101011100 *
b101011100 M
b101011100 O
1!
#880
0!
#885
b101100100 )
b101100100 N
b101100000 *
b101100000 M
b101100000 O
1!
#890
0!
#895
b101101000 )
b101101000 N
b101100100 *
b101100100 M
b101100100 O
1!
#900
0!
#905
b101101100 )
b101101100 N
b101101000 *
b101101000 M
b101101000 O
1!
#910
0!
#915
b101110000 )
b101110000 N
b101101100 *
b101101100 M
b101101100 O
1!
#920
0!
#925
b101110100 )
b101110100 N
b101110000 *
b101110000 M
b101110000 O
1!
#930
0!
#935
b101111000 )
b101111000 N
b101110100 *
b101110100 M
b101110100 O
1!
#940
0!
#945
b101111100 )
b101111100 N
b101111000 *
b101111000 M
b101111000 O
1!
#950
0!
#955
b110000000 )
b110000000 N
b101111100 *
b101111100 M
b101111100 O
1!
#960
0!
#965
b110000100 )
b110000100 N
b110000000 *
b110000000 M
b110000000 O
1!
#970
0!
#975
b110001000 )
b110001000 N
b110000100 *
b110000100 M
b110000100 O
1!
#980
0!
#985
b110001100 )
b110001100 N
b110001000 *
b110001000 M
b110001000 O
1!
#990
0!
#995
b110010000 )
b110010000 N
b110001100 *
b110001100 M
b110001100 O
1!
#1000
0!
#1005
b110010100 )
b110010100 N
b110010000 *
b110010000 M
b110010000 O
1!
